strada/__init__.py
strada/common.py
strada/custom_types.py
strada/debug_logger.py
strada/error_codes.py
strada/exception.py
strada/exception_handler.py
strada/google_mail.py
strada/google_sheets.py
strada/hubspot.py
strada/jira.py
strada/lithic.py
strada/openai.py
strada/rest.py
strada/sdk.py
strada/slack.py
strada/strada_email.py
strada/zendesk.py
strada/zuora.py
strada/aws/__init__.py
strada/aws/ses.py
tests/__init__.py
tests/test_common.py
tests/test_common_hydrate_input_fields.py
tests/test_decorators_exception_handler.py
tests/test_decorators_exception_handler_with_indent.py
tests/test_http_request_executor.py
strada-1.0.65.dist-info/METADATA
strada-1.0.65.dist-info/WHEEL
strada-1.0.65.dist-info/top_level.txt
strada-1.0.65.dist-info/RECORD
