Metadata-Version: 2.1
Name: strada
Version: 1.0.65
Summary: Strada SDK
Author: Strada
Requires-Dist: boto3
Requires-Dist: pydantic
Requires-Dist: jsonschema
Requires-Dist: openai
Requires-Dist: google-api-python-client
Requires-Dist: google-auth
Requires-Dist: oauth2client
Requires-Dist: google-auth-oauthlib
Requires-Dist: google-auth-httplib2
Requires-Dist: requests
